LICENSE
README.rst
setup.py
stack_snapshot.py
stack_snapshot.egg-info/PKG-INFO
stack_snapshot.egg-info/SOURCES.txt
stack_snapshot.egg-info/dependency_links.txt
stack_snapshot.egg-info/requires.txt
stack_snapshot.egg-info/top_level.txt