Metadata-Version: 2.1
Name: stack-snapshot
Version: 1.0.4.3
Summary: A library that automatically captures the complete stack frames including local and global variables when any exceptions occur. 一个在发生异常时，自动捕获异常发生时的完整栈帧，包括局部、全局变量的库。
Home-page: https://github.com/qfcy/PySnapshot
Author: qfcy
Author-email: 3076711200@qq.com
Keywords: stack,dump,exception,debug,bug tracking,stack frame,debugger,heap
Classifier: Programming Language :: Python
Classifier: Topic :: Utilities
Classifier: Topic :: Software Development :: Bug Tracking
Classifier: Topic :: Software Development :: Debuggers
Classifier: Topic :: Software Development :: Testing
Classifier: Topic :: Software Development :: Libraries :: Python Modules
License-File: LICENSE
